redditmon/__init__.py
redditmon/redditmon.py
redditmon-1.0.1.dist-info/LICENSE
redditmon-1.0.1.dist-info/METADATA
redditmon-1.0.1.dist-info/WHEEL
redditmon-1.0.1.dist-info/entry_points.txt
redditmon-1.0.1.dist-info/top_level.txt
redditmon-1.0.1.dist-info/RECORD
