Metadata-Version: 2.1
Name: redditmon
Version: 1.0.1
Summary: A simple package for viewing reddit posts
Home-page: https://github.com/cummings-chris/redditmon
Author: Chris Cummings
Author-email: nouser@slash64.tech
License: MIT
Platform: UNKNOWN
Classifier: Programming Language :: Python :: 3
Classifier: License :: OSI Approved :: MIT License
Classifier: Operating System :: OS Independent
Requires-Python: >=3.6
Requires-Dist: praw
